{
		"id":0,
		"name":"rootTask",
		"children":[
		{
			"id":17,
			"name":"title",
			"description":"description",
			"children":[]
		},
		{
			"id":18,
			"name":"title",
			"description":"description",
			"children":[]
		},
		{
			"id":19,
			"name":"title",
			"description":"description",
			"children":[]
		},
		{
			"id":20,
			"name":"title",
			"description":"description",
			"children":[]
		},
		{
			"id":9,
			"name":"title",
			"description":"description",
			"children":[]
		},
		{
			"id":10,
			"name":"title",
			"description":"description",
			"children":[]
		},
		{
			"id":11,
			"name":"title",
			"description":"description",
			"children":[]
		},
		{
			"id":12,
			"name":"title",
			"description":"description",
			"children":[]
		},
		{
			"id":13,
			"name":"title",
			"description":"description",
			"children":[]
		},
		{
			"id":15,
			"name":"title",
			"description":"description",
			"children":[]
		},
		{
			"id":21,
			"name":"title",
			"description":"description",
			"children":[]
		},
		{
			"id":23,
			"name":"title",
			"description":"description",
			"children":[]
		},
		{
			"id":28,
			"name":"title",
			"description":"description",
			"children":[]
		},
		{
			"id":29,
			"name":"title",
			"description":"description",
			"children":[]
		},
		{
			"id":24,
			"name":"title",
			"description":"description",
			"children":[]
		},
		{
			"id":25,
			"name":"title",
			"description":"description",
			"children":[]
		},
		{
			"id":26,
			"name":"title",
			"description":"description",
			"children":[]
		},
		{
			"id":31,
			"name":"title",
			"description":"description",
			"children":[]
		},
		{
			"id":32,
			"name":"title",
			"description":"description",
			"children":[]
		},
		{
			"id":37,
			"name":"title",
			"description":"description",
			"children":[]
		},
		{
			"id":6,
			"name":"title",
			"description":"description",
			"children":[]
		},
		{
			"id":7,
			"name":"title",
			"description":"description",
			"children":[]
		},
		{
			"id":38,
			"name":"a  new title",
			"description":"descr",
			"color": "#ff0083",
			"children":[]
		}
		]

}